plot_yar/__init__.py
plot_yar/plot.py
plot_yar-0.3.dist-info/LICENSE
plot_yar-0.3.dist-info/METADATA
plot_yar-0.3.dist-info/WHEEL
plot_yar-0.3.dist-info/top_level.txt
plot_yar-0.3.dist-info/RECORD
