Metadata-Version: 2.1
Name: plot-yar
Version: 0.3
Summary: Plotting_graphs
Home-page: https://github.com/yarvod/plot_yar
Author-email: vodyar00@mail.ru
License: UNKNOWN
Platform: UNKNOWN
Classifier: Programming Language :: Python :: 3.8
Classifier: License :: OSI Approved :: MIT License
Classifier: Operating System :: OS Independent
